kpa/__init__.py
kpa/cache_utils.py
kpa/command_line.py
kpa/csv_utils.py
kpa/dev_utils.py
kpa/func_cache_utils.py
kpa/func_utils.py
kpa/html_utils.py
kpa/http_server.py
kpa/http_utils.py
kpa/iter_utils.py
kpa/lazy_utils.py
kpa/llm_utils.py
kpa/math_utils.py
kpa/pip_utils.py
kpa/py.typed
kpa/pypi_utils.py
kpa/repr_utils.py
kpa/skel.py
kpa/speak_utils.py
kpa/terminal_utils.py
kpa/unglob.py
kpa/version.py
kpa/watcher.py
kpa-1.0.52.dist-info/entry_points.txt
kpa-1.0.52.dist-info/WHEEL
kpa-1.0.52.dist-info/METADATA
kpa-1.0.52.dist-info/RECORD
