Metadata-Version: 2.4
Name: kpa
Version: 1.0.52
Summary: Simple python utils
Author-email: Peter VandeHaar <pjvandehaar@gmail.com>
Requires-Python: >=3.8
Classifier: Programming Language :: Python :: 3 :: Only
Classifier: Operating System :: Unix
Project-URL: Home, https://github.com/pjvandehaar/kpa
